{
  "indexes": [
    {
      "collectionGroup": "posts",
      "queryScope": "COLLECTION",
      "fields": [
        {
          "fieldPath": "authorId",
          "order": "ASCENDING"
        },
        {
          "fieldPath": "createdAt",
          "order": "DESCENDING"
        }
      ]
    },
    {
      "collectionGroup": "posts",
      "queryScope": "COLLECTION",
      "fields": [
        {
          "fieldPath": "authorId",
          "order": "ASCENDING"
        },
        {
          "fieldPath": "postStatus",
          "order": "ASCENDING"
        },
        {
          "fieldPath": "createdAt",
          "order": "DESCENDING"
        }
      ]
    },
    {
      "collectionGroup": "posts",
      "queryScope": "COLLECTION",
      "fields": [
        {
          "fieldPath": "authorId",
          "order": "ASCENDING"
        },
        {
          "fieldPath": "isScheduled",
          "order": "ASCENDING"
        },
        {
          "fieldPath": "scheduledAt",
          "order": "ASCENDING"
        }
      ]
    },
    {
      "collectionGroup": "posts",
      "queryScope": "COLLECTION",
      "fields": [
        {
          "fieldPath": "postStatus",
          "order": "ASCENDING"
        },
        {
          "fieldPath": "createdAt",
          "order": "DESCENDING"
        }
      ]
    },
    {
      "collectionGroup": "posts",
      "queryScope": "COLLECTION",
      "fields": [
        {
          "fieldPath": "postStatus",
          "order": "ASCENDING"
        },
        {
          "fieldPath": "scheduledAt",
          "order": "ASCENDING"
        }
      ]
    },
    {
      "collectionGroup": "posts",
      "queryScope": "COLLECTION",
      "fields": [
        {
          "fieldPath": "isScheduled",
          "order": "ASCENDING"
        },
        {
          "fieldPath": "postStatus",
          "order": "ASCENDING"
        },
        {
          "fieldPath": "scheduledAt",
          "order": "ASCENDING"
        }
      ]
    },
    {
      "collectionGroup": "posts",
      "queryScope": "COLLECTION",
      "fields": [
        {
          "fieldPath": "hashtags",
          "arrayConfig": "CONTAINS"
        },
        {
          "fieldPath": "postStatus",
          "order": "ASCENDING"
        },
        {
          "fieldPath": "createdAt",
          "order": "DESCENDING"
        }
      ]
    },
    {
      "collectionGroup": "posts",
      "queryScope": "COLLECTION",
      "fields": [
        {
          "fieldPath": "isPublic",
          "order": "ASCENDING"
        },
        {
          "fieldPath": "postStatus",
          "order": "ASCENDING"
        },
        {
          "fieldPath": "createdAt",
          "order": "DESCENDING"
        }
      ]
    },
    {
      "collectionGroup": "posts",
      "queryScope": "COLLECTION",
      "fields": [
        {
          "fieldPath": "authorId",
          "order": "ASCENDING"
        },
        {
          "fieldPath": "postStatus",
          "order": "ASCENDING"
        },
        {
          "fieldPath": "scheduledAt",
          "order": "ASCENDING"
        }
      ]
    },
    {
      "collectionGroup": "comments",
      "queryScope": "COLLECTION_GROUP",
      "fields": [
        {
          "fieldPath": "postId",
          "order": "ASCENDING"
        },
        {
          "fieldPath": "createdAt",
          "order": "DESCENDING"
        }
      ]
    },
    {
      "collectionGroup": "comments",
      "queryScope": "COLLECTION_GROUP",
      "fields": [
        {
          "fieldPath": "authorId",
          "order": "ASCENDING"
        },
        {
          "fieldPath": "createdAt",
          "order": "DESCENDING"
        }
      ]
    },
    {
      "collectionGroup": "likes",
      "queryScope": "COLLECTION_GROUP",
      "fields": [
        {
          "fieldPath": "postId",
          "order": "ASCENDING"
        },
        {
          "fieldPath": "createdAt",
          "order": "DESCENDING"
        }
      ]
    },
    {
      "collectionGroup": "notifications",
      "queryScope": "COLLECTION_GROUP",
      "fields": [
        {
          "fieldPath": "userId",
          "order": "ASCENDING"
        },
        {
          "fieldPath": "read",
          "order": "ASCENDING"
        },
        {
          "fieldPath": "createdAt",
          "order": "DESCENDING"
        }
      ]
    },
    {
      "collectionGroup": "notifications",
      "queryScope": "COLLECTION_GROUP",
      "fields": [
        {
          "fieldPath": "userId",
          "order": "ASCENDING"
        },
        {
          "fieldPath": "type",
          "order": "ASCENDING"
        },
        {
          "fieldPath": "createdAt",
          "order": "DESCENDING"
        }
      ]
    }
  ],
  "fieldOverrides": [
    {
      "collectionGroup": "posts",
      "fieldPath": "hashtags",
      "ttl": false,
      "indexes": [
        {
          "order": "ASCENDING",
          "queryScope": "COLLECTION"
        },
        {
          "arrayConfig": "CONTAINS",
          "queryScope": "COLLECTION"
        }
      ]
    },
    {
      "collectionGroup": "posts",
      "fieldPath": "scheduledAt",
      "ttl": false,
      "indexes": [
        {
          "order": "ASCENDING",
          "queryScope": "COLLECTION"
        },
        {
          "order": "DESCENDING",
          "queryScope": "COLLECTION"
        }
      ]
    }
  ]
}